<object-stream>
  <com.fatwire.realtime.ResourceDataImpl>
    <id class="string">GS_SiteVisitor_P</id>
    <resourceType>ASSET_TYPE</resourceType>
    <deps class="empty-set"/>
    <data class="com.fatwire.realtime.AssetTypeWrapper">
      <assettypeDescriptor class="com.openmarket.gator.flexgroups.FlexGroupTypeDescriptor">
        <assettype>GS_SiteVisitor_P</assettype>
        <plural>Site Visitor Ps</plural>
        <logic>com.openmarket.assetframework.complexasset.ComplexAsset</logic>
        <description>Site Visitor P</description>
        <usesearchindex>0</usesearchindex>
        <indexfile></indexfile>
        <urldescriptorspec>C:\OracleWebCenterSites\11gR1\App_Server\apache-tomcat-6.0.32\temp\fwcs-tmp\temp31\dcs5294024690309579462.tmp</urldescriptorspec>
        <canbechild>T</canbechild>
        <uid>85b42a19-3610-4024-b8d9-65eff8b82c26</uid>
        <useDimension></useDimension>
        <complexAssetClass>com.openmarket.gator.flexgroups.FlexGroupManager</complexAssetClass>
        <assetCategory>Catalog</assetCategory>
        <template>GS_SiteVisitor_PD</template>
        <attr>GS_SiteVisitor_A</attr>
      </assettypeDescriptor>
      <systemInfoIList class="com.openmarket.xcelerate.util.GeneralListCopy">
        <count>1</count>
        <currentRow>0</currentRow>
        <atEndFlag>false</atEndFlag>
        <columnNames>
          <string>metadata</string>
          <string>systable</string>
          <string>tblname</string>
          <string>defdir</string>
          <string>acl</string>
        </columnNames>
        <columnCount>5</columnCount>
        <indColumnNames/>
        <indColumnCount>0</indColumnCount>
        <isURLColumn>
          <boolean>false</boolean>
          <boolean>false</boolean>
          <boolean>false</boolean>
          <boolean>false</boolean>
          <boolean>false</boolean>
        </isURLColumn>
        <hashTable>
          <strings>
            <string></string>
            <string>Browser,SiteGod,xceleditor,xceladmin</string>
            <null/>
            <null/>
            <null/>
            <null/>
            <null/>
            <null/>
            <string>obj</string>
            <null/>
            <null/>
            <null/>
            <null/>
            <null/>
            <null/>
            <null/>
            <string>GS_SiteVisitor_P</string>
            <null/>
            <null/>
            <null/>
            <null/>
            <null/>
            <null/>
            <null/>
            <string>C:\OracleWebCenterSites\11gR1\ContentServer\11.1.1.6.0\Shared\Storage\GS_SiteVisitor_P\</string>
            <null/>
            <null/>
            <null/>
            <null/>
            <null/>
            <null/>
            <null/>
          </strings>
          <bytes>
            <null/>
            <null/>
            <null/>
            <null/>
            <null/>
            <null/>
            <null/>
            <null/>
            <null/>
            <null/>
            <null/>
            <null/>
            <null/>
            <null/>
            <null/>
            <null/>
            <null/>
            <null/>
            <null/>
            <null/>
            <null/>
            <null/>
            <null/>
            <null/>
            <null/>
            <null/>
            <null/>
            <null/>
            <null/>
            <null/>
            <null/>
            <null/>
          </bytes>
          <columns>
            <int>0</int>
            <int>4</int>
            <int>0</int>
            <int>0</int>
            <int>0</int>
            <int>0</int>
            <int>0</int>
            <int>0</int>
            <int>1</int>
            <int>0</int>
            <int>0</int>
            <int>0</int>
            <int>0</int>
            <int>0</int>
            <int>0</int>
            <int>0</int>
            <int>2</int>
            <int>0</int>
            <int>0</int>
            <int>0</int>
            <int>0</int>
            <int>0</int>
            <int>0</int>
            <int>0</int>
            <int>3</int>
            <int>0</int>
            <int>0</int>
            <int>0</int>
            <int>0</int>
            <int>0</int>
            <int>0</int>
            <int>0</int>
          </columns>
          <rows>
            <int>0</int>
            <int>0</int>
            <int>-1</int>
            <int>-1</int>
            <int>-1</int>
            <int>-1</int>
            <int>-1</int>
            <int>-1</int>
            <int>0</int>
            <int>-1</int>
            <int>-1</int>
            <int>-1</int>
            <int>-1</int>
            <int>-1</int>
            <int>-1</int>
            <int>-1</int>
            <int>0</int>
            <int>-1</int>
            <int>-1</int>
            <int>-1</int>
            <int>-1</int>
            <int>-1</int>
            <int>-1</int>
            <int>-1</int>
            <int>0</int>
            <int>-1</int>
            <int>-1</int>
            <int>-1</int>
            <int>-1</int>
            <int>-1</int>
            <int>-1</int>
            <int>-1</int>
          </rows>
          <hashsize>32</hashsize>
          <hashfull>24</hashfull>
          <hashcount>5</hashcount>
        </hashTable>
        <columnHash>
          <entry>
            <string>tblname</string>
            <int>2</int>
          </entry>
          <entry>
            <string>systable</string>
            <int>1</int>
          </entry>
          <entry>
            <string>metadata</string>
            <int>0</int>
          </entry>
          <entry>
            <string>defdir</string>
            <int>3</int>
          </entry>
          <entry>
            <string>acl</string>
            <int>4</int>
          </entry>
        </columnHash>
      </systemInfoIList>
      <systemSQLIList class="com.openmarket.xcelerate.util.GeneralListCopy">
        <count>1</count>
        <currentRow>0</currentRow>
        <atEndFlag>false</atEndFlag>
        <columnNames>
          <string>description</string>
          <string>deftable</string>
          <string>qryname</string>
          <string>url</string>
        </columnNames>
        <columnCount>4</columnCount>
        <indColumnNames>
          <string>@url</string>
        </indColumnNames>
        <indColumnCount>1</indColumnCount>
        <isURLColumn>
          <boolean>false</boolean>
          <boolean>false</boolean>
          <boolean>false</boolean>
          <boolean>true</boolean>
        </isURLColumn>
        <hashTable>
          <strings>
            <string></string>
            <null/>
            <null/>
            <null/>
            <null/>
            <null/>
            <null/>
            <null/>
            <string>GS_SiteVisitor_P,AssetPublication</string>
            <null/>
            <null/>
            <null/>
            <null/>
            <null/>
            <null/>
            <null/>
            <string>OpenMarket/Xcelerate/AssetType/GS_SiteVisitor_P/SelectSummary</string>
            <null/>
            <null/>
            <null/>
            <null/>
            <null/>
            <null/>
            <null/>
            <string>OpenMarket\Xcelerate\AssetType\GS_SiteVisitor_P\SelectSummary.sql</string>
            <null/>
            <null/>
            <null/>
            <null/>
            <null/>
            <null/>
            <null/>
          </strings>
          <bytes>
            <null/>
            <null/>
            <null/>
            <null/>
            <null/>
            <null/>
            <null/>
            <null/>
            <null/>
            <null/>
            <null/>
            <null/>
            <null/>
            <null/>
            <null/>
            <null/>
            <null/>
            <null/>
            <null/>
            <null/>
            <null/>
            <null/>
            <null/>
            <null/>
            <byte-array>U0VMRUNUIA0KICAgVmFyaWFibGVzLkFzc2V0VHlwZS5pZCwNCiAgIFZhcmlhYmxlcy5Bc3NldFR5
cGUuY3JlYXRlZGRhdGUsDQogICBWYXJpYWJsZXMuQXNzZXRUeXBlLmNyZWF0ZWRieSwNCiAgIFZh
cmlhYmxlcy5Bc3NldFR5cGUudXBkYXRlZGRhdGUsDQogICBWYXJpYWJsZXMuQXNzZXRUeXBlLnVw
ZGF0ZWRieSAsDQogICBWYXJpYWJsZXMuQXNzZXRUeXBlLm5hbWUgICwNCiAgIFZhcmlhYmxlcy5B
c3NldFR5cGUuZGVzY3JpcHRpb24gLA0KICAgVmFyaWFibGVzLkFzc2V0VHlwZS5mbGV4Z3JvdXB0
ZW1wbGF0ZWlkIEFTIGZ0ZW1wbGF0ZSwNCiAgIFZhcmlhYmxlcy5Bc3NldFR5cGUuc3RhcnRkYXRl
LA0KICAgVmFyaWFibGVzLkFzc2V0VHlwZS5lbmRkYXRlLA0KICAgVmFyaWFibGVzLkFzc2V0VHlw
ZS5zdGF0dXMgDQpGUk9NIA0KICAgIFZhcmlhYmxlcy5Bc3NldFR5cGUsQXNzZXRQdWJsaWNhdGlv
biANCldIRVJFIA0KICAgIFZhcmlhYmxlcy5Bc3NldFR5cGUuaWQgPSBBc3NldFB1YmxpY2F0aW9u
LmFzc2V0aWQgDQogICBBTkQgKEFzc2V0UHVibGljYXRpb24ucHViaWQgPSBTZXNzaW9uVmFyaWFi
bGVzLnB1YmlkIE9SIEFzc2V0UHVibGljYXRpb24ucHViaWQ9MCkNCiAgIEFORCBWYXJpYWJsZXMu
QXNzZXRUeXBlLnN0YXR1cyE9J1ZPJw0KICAgQU5EIFZhcmlhYmxlcy5Bc3NldFR5cGUuc3RhdHVz
IT0nUFInICANCiAgIFZhcmlhYmxlcy5xdWVyeWVuZA0KDQo=</byte-array>
            <null/>
            <null/>
            <null/>
            <null/>
            <null/>
            <null/>
            <null/>
          </bytes>
          <columns>
            <int>0</int>
            <int>0</int>
            <int>0</int>
            <int>0</int>
            <int>0</int>
            <int>0</int>
            <int>0</int>
            <int>0</int>
            <int>1</int>
            <int>0</int>
            <int>0</int>
            <int>0</int>
            <int>0</int>
            <int>0</int>
            <int>0</int>
            <int>0</int>
            <int>2</int>
            <int>0</int>
            <int>0</int>
            <int>0</int>
            <int>0</int>
            <int>0</int>
            <int>0</int>
            <int>0</int>
            <int>3</int>
            <int>0</int>
            <int>0</int>
            <int>0</int>
            <int>0</int>
            <int>0</int>
            <int>0</int>
            <int>0</int>
          </columns>
          <rows>
            <int>0</int>
            <int>-1</int>
            <int>-1</int>
            <int>-1</int>
            <int>-1</int>
            <int>-1</int>
            <int>-1</int>
            <int>-1</int>
            <int>0</int>
            <int>-1</int>
            <int>-1</int>
            <int>-1</int>
            <int>-1</int>
            <int>-1</int>
            <int>-1</int>
            <int>-1</int>
            <int>0</int>
            <int>-1</int>
            <int>-1</int>
            <int>-1</int>
            <int>-1</int>
            <int>-1</int>
            <int>-1</int>
            <int>-1</int>
            <int>0</int>
            <int>-1</int>
            <int>-1</int>
            <int>-1</int>
            <int>-1</int>
            <int>-1</int>
            <int>-1</int>
            <int>-1</int>
          </rows>
          <hashsize>32</hashsize>
          <hashfull>24</hashfull>
          <hashcount>4</hashcount>
        </hashTable>
        <columnHash>
          <entry>
            <string>deftable</string>
            <int>1</int>
          </entry>
          <entry>
            <string>qryname</string>
            <int>2</int>
          </entry>
          <entry>
            <string>url</string>
            <int>3</int>
          </entry>
          <entry>
            <string>description</string>
            <int>0</int>
          </entry>
        </columnHash>
      </systemSQLIList>
      <subtypes/>
      <associations/>
      <siteNames class="list">
        <string>EGiftShop</string>
      </siteNames>
    </data>
  </com.fatwire.realtime.ResourceDataImpl>
</object-stream>
<!--==================___ METADATA ___================
<dependencies>
  <list>
    <dependency>
      <depType>E</depType>
      <resType>@ASSET_TYPE</resType>
      <resId>GS_SiteVisitor_P</resId>
      <uid>85b42a19-3610-4024-b8d9-65eff8b82c26</uid>
    </dependency>
    <dependency>
      <depType>E</depType>
      <resType>@ASSET_TYPE</resType>
      <resId>GS_SiteVisitor_A</resId>
      <uid>603feeb1-88f3-41a4-b88e-8e85de20f5b6</uid>
    </dependency>
    <dependency>
      <depType>E</depType>
      <resType>@ASSET_TYPE</resType>
      <resId>GS_SiteVisitor_PD</resId>
      <uid>ef7f624a-4389-4d80-b2a4-d8eafdf22b12</uid>
    </dependency>
    <dependency>
      <depType>E</depType>
      <resType>@ELEMENTCATALOG</resType>
      <resId>OpenMarket/Xcelerate/AssetType/GS_SiteVisitor_P/AppendSelectDetails</resId>
      <uid>OpenMarket/Xcelerate/AssetType/GS_SiteVisitor_P/AppendSelectDetails</uid>
    </dependency>
    <dependency>
      <depType>E</depType>
      <resType>@ELEMENTCATALOG</resType>
      <resId>OpenMarket/Xcelerate/AssetType/GS_SiteVisitor_P/AppendSelectDetailsSE</resId>
      <uid>OpenMarket/Xcelerate/AssetType/GS_SiteVisitor_P/AppendSelectDetailsSE</uid>
    </dependency>
    <dependency>
      <depType>E</depType>
      <resType>@ELEMENTCATALOG</resType>
      <resId>OpenMarket/Xcelerate/AssetType/GS_SiteVisitor_P/ContentDetails</resId>
      <uid>OpenMarket/Xcelerate/AssetType/GS_SiteVisitor_P/ContentDetails</uid>
    </dependency>
    <dependency>
      <depType>E</depType>
      <resType>@ELEMENTCATALOG</resType>
      <resId>OpenMarket/Xcelerate/AssetType/GS_SiteVisitor_P/ContentForm</resId>
      <uid>OpenMarket/Xcelerate/AssetType/GS_SiteVisitor_P/ContentForm</uid>
    </dependency>
    <dependency>
      <depType>E</depType>
      <resType>@ELEMENTCATALOG</resType>
      <resId>OpenMarket/Xcelerate/AssetType/GS_SiteVisitor_P/IndexAdd</resId>
      <uid>OpenMarket/Xcelerate/AssetType/GS_SiteVisitor_P/IndexAdd</uid>
    </dependency>
    <dependency>
      <depType>E</depType>
      <resType>@ELEMENTCATALOG</resType>
      <resId>OpenMarket/Xcelerate/AssetType/GS_SiteVisitor_P/IndexCreateVerity</resId>
      <uid>OpenMarket/Xcelerate/AssetType/GS_SiteVisitor_P/IndexCreateVerity</uid>
    </dependency>
    <dependency>
      <depType>E</depType>
      <resType>@ELEMENTCATALOG</resType>
      <resId>OpenMarket/Xcelerate/AssetType/GS_SiteVisitor_P/IndexReplace</resId>
      <uid>OpenMarket/Xcelerate/AssetType/GS_SiteVisitor_P/IndexReplace</uid>
    </dependency>
    <dependency>
      <depType>E</depType>
      <resType>@ELEMENTCATALOG</resType>
      <resId>OpenMarket/Xcelerate/AssetType/GS_SiteVisitor_P/LoadSiteTree</resId>
      <uid>OpenMarket/Xcelerate/AssetType/GS_SiteVisitor_P/LoadSiteTree</uid>
    </dependency>
    <dependency>
      <depType>E</depType>
      <resType>@ELEMENTCATALOG</resType>
      <resId>OpenMarket/Xcelerate/AssetType/GS_SiteVisitor_P/LoadTree</resId>
      <uid>OpenMarket/Xcelerate/AssetType/GS_SiteVisitor_P/LoadTree</uid>
    </dependency>
    <dependency>
      <depType>E</depType>
      <resType>@ELEMENTCATALOG</resType>
      <resId>OpenMarket/Xcelerate/AssetType/GS_SiteVisitor_P/PostUpdate</resId>
      <uid>OpenMarket/Xcelerate/AssetType/GS_SiteVisitor_P/PostUpdate</uid>
    </dependency>
    <dependency>
      <depType>E</depType>
      <resType>@ELEMENTCATALOG</resType>
      <resId>OpenMarket/Xcelerate/AssetType/GS_SiteVisitor_P/PreUpdate</resId>
      <uid>OpenMarket/Xcelerate/AssetType/GS_SiteVisitor_P/PreUpdate</uid>
    </dependency>
    <dependency>
      <depType>E</depType>
      <resType>@ELEMENTCATALOG</resType>
      <resId>OpenMarket/Xcelerate/AssetType/GS_SiteVisitor_P/Render</resId>
      <uid>OpenMarket/Xcelerate/AssetType/GS_SiteVisitor_P/Render</uid>
    </dependency>
    <dependency>
      <depType>E</depType>
      <resType>@ELEMENTCATALOG</resType>
      <resId>OpenMarket/Xcelerate/AssetType/GS_SiteVisitor_P/SearchForm</resId>
      <uid>OpenMarket/Xcelerate/AssetType/GS_SiteVisitor_P/SearchForm</uid>
    </dependency>
    <dependency>
      <depType>E</depType>
      <resType>@ELEMENTCATALOG</resType>
      <resId>OpenMarket/Xcelerate/AssetType/GS_SiteVisitor_P/SearchWithSubtype</resId>
      <uid>OpenMarket/Xcelerate/AssetType/GS_SiteVisitor_P/SearchWithSubtype</uid>
    </dependency>
    <dependency>
      <depType>E</depType>
      <resType>@ELEMENTCATALOG</resType>
      <resId>OpenMarket/Xcelerate/AssetType/GS_SiteVisitor_P/Tile</resId>
      <uid>OpenMarket/Xcelerate/AssetType/GS_SiteVisitor_P/Tile</uid>
    </dependency>
  </list>
</dependencies>
==================______________________==================
#
#Sat Feb 09 08:37:53 IST 2013
key=@ASSET_TYPE-85b42a19-3610-4024-b8d9-65eff8b82c26
type=ASSET_TYPE
sites=EGiftShop

==================___ END METADATA ___==================-->
